spurdify/__init__.py
spurdify/client.py
spurdify-0.3.0.dist-info/LICENSE
spurdify-0.3.0.dist-info/METADATA
spurdify-0.3.0.dist-info/WHEEL
spurdify-0.3.0.dist-info/top_level.txt
spurdify-0.3.0.dist-info/RECORD
