Metadata-Version: 2.1
Name: spurdify
Version: 0.3.0
Summary: Spurdify any text to sound like Spurod Spardo wrote it!
Home-page: https://github.com/obviyus/spurdify
Author: obviyus
Author-email: hi@obviy.us
License: UNKNOWN
Keywords: spurdo spurdify regex
Platform: UNKNOWN
Classifier: Programming Language :: Python :: 3
Classifier: License :: OSI Approved :: GNU General Public License v3 (GPLv3)
Classifier: Operating System :: OS Independent
Requires-Python: >=3.6
